README.md
setup.py
smux.py
smux.egg-info/PKG-INFO
smux.egg-info/SOURCES.txt
smux.egg-info/dependency_links.txt
smux.egg-info/top_level.txt