Metadata-Version: 1.0
Name: smux
Version: 0.6
Summary: Simple tmux launcher that will take less than 2 minutes to learn and should work across all versions of tmux
Home-page: https://github.com/hq6/smux
Author: Henry Qin
Author-email: root@hq6.me
License: MIT
Platform: All platforms that tmux runs on.
